augratin/__init__.py
augratin/__main__.py
augratin/data/JetBrainsMono-Regular.ttf
augratin/data/dialog.ui
augratin/data/k6gte-augratin-128.png
augratin/data/k6gte-augratin-32.png
augratin/data/k6gte-augratin-64.png
augratin/data/k6gte-augratin.desktop
augratin/lib/__init__.py
augratin/lib/cat_interface.py
augratin/lib/omnirig_interface.py
augratin/lib/udp_broadcast.py
augratin/lib/version.py
augratin-25.5.18.dist-info/licenses/LICENSE
augratin-25.5.18.dist-info/METADATA
augratin-25.5.18.dist-info/WHEEL
augratin-25.5.18.dist-info/entry_points.txt
augratin-25.5.18.dist-info/top_level.txt
augratin-25.5.18.dist-info/RECORD
