Metadata-Version: 2.4
Name: augratin
Version: 25.5.18
Summary: An aid for POTA hunters
Author-email: Michael Bridak <michael.bridak@gmail.com>
Project-URL: Homepage, https://github.com/mbridak/augratin
Project-URL: Bug Tracker, https://github.com/mbridak/augratin/issues
Classifier: Programming Language :: Python :: 3
Classifier: Development Status :: 5 - Production/Stable
Classifier: License :: OSI Approved :: GNU General Public License v3 (GPLv3)
Classifier: Environment :: X11 Applications :: Qt
Classifier: Operating System :: POSIX :: Linux
Classifier: Intended Audience :: End Users/Desktop
Classifier: Natural Language :: English
Classifier: Topic :: Communications :: Ham Radio
Requires-Python: >=3.9
License-File: LICENSE
Requires-Dist: PyQt6
Requires-Dist: PyQt6-WebEngine
Requires-Dist: requests
Requires-Dist: psutil
Requires-Dist: folium
Requires-Dist: pywin32; os_name == "nt"
Dynamic: license-file
